pawnshop/ChessBoard.py
pawnshop/ChessVector.py
pawnshop/Exceptions.py
pawnshop/GameNotations.py
pawnshop/Moves.py
pawnshop/Pieces.py
pawnshop/Utils.py
pawnshop/__init__.py
pawnshop/configurations/ClassicConfig.py
pawnshop/configurations/DefaultConfig.JSON
pawnshop/configurations/FourPlayerConfig.py
pawnshop/configurations/__init__.py
pawnshop-1.0.3.dist-info/LICENSE
pawnshop-1.0.3.dist-info/METADATA
pawnshop-1.0.3.dist-info/WHEEL
pawnshop-1.0.3.dist-info/top_level.txt
pawnshop-1.0.3.dist-info/RECORD
