Metadata-Version: 2.1
Name: pawnshop
Version: 1.0.3
Summary: A simple chess library as hobby project.
Home-page: https://github.com/NilsForssen/pawnshop
Author: Nils Forssén
Author-email: forssennils@gmail.com
License: UNKNOWN
Platform: UNKNOWN
Classifier: Programming Language :: Python :: 3
Classifier: License :: OSI Approved :: MIT License
Classifier: Operating System :: OS Independent
Requires-Python: >=3.6
License-File: LICENSE
